fbsak/__init__.py
fbsak/baseclasses/__init__.py
fbsak/baseclasses/logging.py
fbsak/graphql/__init__.py
fbsak/graphql/schemagen/__init__.py
fbsak/graphql/schemagen/extra.py
fbsak/graphql/schemagen/hooks.py
fbsak/graphql/schemagen/utilities.py
fbsak/sqlalchemy/__init__.py
fbsak/sqlalchemy/compositetypes/__init__.py
tests/__init__.py
fbsak-0.9.6.dist-info/LICENSE
fbsak-0.9.6.dist-info/METADATA
fbsak-0.9.6.dist-info/WHEEL
fbsak-0.9.6.dist-info/top_level.txt
fbsak-0.9.6.dist-info/RECORD
